[
  {
    "identifier": 750100018,
    "pathology": "Générales",
    "patientType": "Adultes",
    "phoneNumber": "01 42 34 82 32",
    "openingDays": "7j sur 7",
    "monday": "24h sur 24",
    "tuesday": "24h sur 24",
    "wednesday": "24h sur 24",
    "thursday": "24h sur 24",
    "friday": "24h sur 24",
    "saturday": "24h sur 24",
    "sunday": "24h sur 24"
  },
  {
    "identifier": 750100042,
    "pathology": "Générales",
    "patientType": "Adultes",
    "phoneNumber": "01 49 95 64 45",
    "openingDays": "7j sur 7",
    "monday": "24h sur 24",
    "tuesday": "24h sur 24",
    "wednesday": "24h sur 24",
    "thursday": "24h sur 24",
    "friday": "24h sur 24",
    "saturday": "24h sur 24",
    "sunday": "24h sur 24"
  },
  {
    "identifier": 750100042,
    "pathology": "Oto-rhino-laryngologiques",
    "patientType": "Adultes",
    "phoneNumber": "01 49 95 65 65",
    "openingDays": "7j sur 7",
    "monday": "24h sur 24",
    "tuesday": "24h sur 24",
    "wednesday": "24h sur 24",
    "thursday": "24h sur 24",
    "friday": "24h sur 24",
    "saturday": "24h sur 24",
    "sunday": "24h sur 24"
  },
  {
    "identifier": 750100042,
    "pathology": "Gynéco-obstétricales",
    "patientType": "Maternité",
    "phoneNumber": "01 49 95 62 37",
    "openingDays": "7j sur 7",
    "monday": "24h sur 24",
    "tuesday": "24h sur 24",
    "wednesday": "24h sur 24",
    "thursday": "24h sur 24",
    "friday": "24h sur 24",
    "saturday": "24h sur 24",
    "sunday": "24h sur 24"
  },
  {
    "identifier": 750100042,
    "pathology": "Psychiatriques",
    "patientType": "Universel",
    "phoneNumber": "01 49 95 64 43",
    "openingDays": "7j sur 7",
    "monday": "24h sur 24",
    "tuesday": "24h sur 24",
    "wednesday": "24h sur 24",
    "thursday": "24h sur 24",
    "friday": "24h sur 24",
    "saturday": "24h sur 24",
    "sunday": "24h sur 24"
  },
  {
    "identifier": 750100075,
    "pathology": "Générales",
    "patientType": "Adultes",
    "phoneNumber": "01 42 49 91 17",
    "openingDays": "7j sur 7",
    "monday": "24h sur 24",
    "tuesday": "24h sur 24",
    "wednesday": "24h sur 24",
    "thursday": "24h sur 24",
    "friday": "24h sur 24",
    "saturday": "24h sur 24",
    "sunday": "24h sur 24"
  },
  {
    "identifier": 750100091,
    "pathology": "Générales",
    "patientType": "Adultes",
    "phoneNumber": "01 49 28 27 08",
    "openingDays": "7j sur 7",
    "monday": "24h sur 24",
    "tuesday": "24h sur 24",
    "wednesday": "24h sur 24",
    "thursday": "24h sur 24",
    "friday": "24h sur 24",
    "saturday": "24h sur 24",
    "sunday": "24h sur 24"
  },
  {
    "identifier": 750100091,
    "pathology": "Plaies de la main",
    "patientType": "Adultes",
    "phoneNumber": "01 49 28 30 00",
    "openingDays": "7j sur 7",
    "monday": "24h sur 24",
    "tuesday": "24h sur 24",
    "wednesday": "24h sur 24",
    "thursday": "24h sur 24",
    "friday": "24h sur 24",
    "saturday": "24h sur 24",
    "sunday": "24h sur 24"
  },
  {
    "identifier": 750100091,
    "pathology": "Psychiatriques",
    "patientType": "Adultes",
    "phoneNumber": "01 49 28 27 08",
    "openingDays": "7j sur 7",
    "monday": "24h sur 24",
    "tuesday": "24h sur 24",
    "wednesday": "24h sur 24",
    "thursday": "24h sur 24",
    "friday": "24h sur 24",
    "saturday": "24h sur 24",
    "sunday": "24h sur 24"
  },
  {
    "identifier": 750100109,
    "pathology": "Gynéco-obstétricales",
    "patientType": "Maternité",
    "phoneNumber": "01 44 73 51 96",
    "openingDays": "7j sur 7",
    "monday": "24h sur 24",
    "tuesday": "24h sur 24",
    "wednesday": "24h sur 24",
    "thursday": "24h sur 24",
    "friday": "24h sur 24",
    "saturday": "24h sur 24",
    "sunday": "24h sur 24"
  },
  {
    "identifier": 750100109,
    "pathology": "Générales",
    "patientType": "Enfants",
    "phoneNumber": "01 44 73 67 40",
    "openingDays": "7j sur 7",
    "monday": "24h sur 24",
    "tuesday": "24h sur 24",
    "wednesday": "24h sur 24",
    "thursday": "24h sur 24",
    "friday": "24h sur 24",
    "saturday": "24h sur 24",
    "sunday": "24h sur 24"
  },
  {
    "identifier": 750100109,
    "pathology": "Psychiatriques",
    "patientType": "Enfants",
    "phoneNumber": "01 44 73 67 40",
    "openingDays": "7j sur 7",
    "monday": "24h sur 24",
    "tuesday": "24h sur 24",
    "wednesday": "24h sur 24",
    "thursday": "24h sur 24",
    "friday": "24h sur 24",
    "saturday": "24h sur 24",
    "sunday": "24h sur 24"
  },
  {
    "identifier": 750100125,
    "pathology": "Générales",
    "patientType": "Adultes",
    "phoneNumber": "",
    "openingDays": "7j sur 7",
    "monday": "24h sur 24",
    "tuesday": "24h sur 24",
    "wednesday": "24h sur 24",
    "thursday": "24h sur 24",
    "friday": "24h sur 24",
    "saturday": "24h sur 24",
    "sunday": "24h sur 24"
  },
  {
    "identifier": 750100125,
    "pathology": "Ophtalmologiques",
    "patientType": "Universel",
    "phoneNumber": "01 42 34 80 36",
    "openingDays": "7j sur 7",
    "monday": "24h sur 24",
    "tuesday": "24h sur 24",
    "wednesday": "24h sur 24",
    "thursday": "24h sur 24",
    "friday": "24h sur 24",
    "saturday": "24h sur 24",
    "sunday": "24h sur 24"
  },
  {
    "identifier": 750100125,
    "pathology": "Dentaires",
    "patientType": "Universel",
    "phoneNumber": "",
    "openingDays": "7j sur 7",
    "monday": "24h sur 24",
    "tuesday": "24h sur 24",
    "wednesday": "24h sur 24",
    "thursday": "24h sur 24",
    "friday": "24h sur 24",
    "saturday": "24h sur 24",
    "sunday": "24h sur 24"
  },
  {
    "identifier": 750100125,
    "pathology": "Gynéco-obstétricales",
    "patientType": "Maternité",
    "phoneNumber": "01 42 17 77 10",
    "openingDays": "7j sur 7",
    "monday": "24h sur 24",
    "tuesday": "24h sur 24",
    "wednesday": "24h sur 24",
    "thursday": "24h sur 24",
    "friday": "24h sur 24",
    "saturday": "24h sur 24",
    "sunday": "24h sur 24"
  },
  {
    "identifier": 750100125,
    "pathology": "Psychiatriques",
    "patientType": "Enfants",
    "phoneNumber": "01 42 16 23 33",
    "openingDays": "Lundi au Samedi",
    "monday": "09h00 - 18h30",
    "tuesday": "09h00 - 18h30",
    "wednesday": "09h00 - 18h30",
    "thursday": "09h00 - 18h30",
    "friday": "09h00 - 18h30",
    "saturday": "09h00 - 13h00",
    "sunday": ""
  },
  {
    "identifier": 750100166,
    "pathology": "Générales",
    "patientType": "Adultes",
    "phoneNumber": "01 58 41 27 22",
    "openingDays": "7j sur 7",
    "monday": "24h sur 24",
    "tuesday": "24h sur 24",
    "wednesday": "24h sur 24",
    "thursday": "24h sur 24",
    "friday": "24h sur 24",
    "saturday": "24h sur 24",
    "sunday": "24h sur 24"
  },
  {
    "identifier": 750100166,
    "pathology": "Psychiatriques",
    "patientType": "Adultes",
    "phoneNumber": "",
    "openingDays": "7j sur 7",
    "monday": "24h sur 24",
    "tuesday": "24h sur 24",
    "wednesday": "24h sur 24",
    "thursday": "24h sur 24",
    "friday": "24h sur 24",
    "saturday": "24h sur 24",
    "sunday": "24h sur 24"
  },
  {
    "identifier": 750100167,
    "pathology": "Gynéco-obstétricales",
    "patientType": "Maternité",
    "phoneNumber": "01 58 41 35 91",
    "openingDays": "7j sur 7",
    "monday": "24h sur 24",
    "tuesday": "24h sur 24",
    "wednesday": "24h sur 24",
    "thursday": "24h sur 24",
    "friday": "24h sur 24",
    "saturday": "24h sur 24",
    "sunday": "24h sur 24"
  },
  {
    "identifier": 750100208,
    "pathology": "Générales",
    "patientType": "Enfants",
    "phoneNumber": "01 44 49 42 90",
    "openingDays": "7j sur 7",
    "monday": "24h sur 24",
    "tuesday": "24h sur 24",
    "wednesday": "24h sur 24",
    "thursday": "24h sur 24",
    "friday": "24h sur 24",
    "saturday": "24h sur 24",
    "sunday": "24h sur 24"
  },
  {
    "identifier": 750100208,
    "pathology": "Psychiatriques",
    "patientType": "Enfants",
    "phoneNumber": "01 44 49 42 90",
    "openingDays": "7j sur 7",
    "monday": "24h sur 24",
    "tuesday": "24h sur 24",
    "wednesday": "24h sur 24",
    "thursday": "24h sur 24",
    "friday": "24h sur 24",
    "saturday": "24h sur 24",
    "sunday": "24h sur 24"
  },
  {
    "identifier": 750100208,
    "pathology": "Oto-rhino-laryngologiques",
    "patientType": "Enfants",
    "phoneNumber": "01 44 49 46 86",
    "openingDays": "7j sur 7",
    "monday": "24h sur 24",
    "tuesday": "24h sur 24",
    "wednesday": "24h sur 24",
    "thursday": "24h sur 24",
    "friday": "24h sur 24",
    "saturday": "24h sur 24",
    "sunday": "24h sur 24"
  },
  {
    "identifier": 750100208,
    "pathology": "Obstétricales",
    "patientType": "Maternité",
    "phoneNumber": "01 44 49 40 00",
    "openingDays": "7j sur 7",
    "monday": "24h sur 24",
    "tuesday": "24h sur 24",
    "wednesday": "24h sur 24",
    "thursday": "24h sur 24",
    "friday": "24h sur 24",
    "saturday": "24h sur 24",
    "sunday": "24h sur 24"
  },
  {
    "identifier": 750100232,
    "pathology": "Générales",
    "patientType": "Adultes",
    "phoneNumber": "01 40 25 80 80",
    "openingDays": "7j sur 7",
    "monday": "24h sur 24",
    "tuesday": "24h sur 24",
    "wednesday": "24h sur 24",
    "thursday": "24h sur 24",
    "friday": "24h sur 24",
    "saturday": "24h sur 24",
    "sunday": "24h sur 24"
  },
  {
    "identifier": 750100232,
    "pathology": "Gynéco-obstétricales",
    "patientType": "Maternité",
    "phoneNumber": "01 40 25 80 80",
    "openingDays": "7j sur 7",
    "monday": "24h sur 24",
    "tuesday": "24h sur 24",
    "wednesday": "24h sur 24",
    "thursday": "24h sur 24",
    "friday": "24h sur 24",
    "saturday": "24h sur 24",
    "sunday": "24h sur 24"
  },
  {
    "identifier": 750100232,
    "pathology": "Psychiatriques",
    "patientType": "Adultes",
    "phoneNumber": "01 53 11 12 40",
    "openingDays": "7j sur 7",
    "monday": "24h sur 24",
    "tuesday": "24h sur 24",
    "wednesday": "24h sur 24",
    "thursday": "24h sur 24",
    "friday": "24h sur 24",
    "saturday": "24h sur 24",
    "sunday": "24h sur 24"
  },
  {
    "identifier": 750100273,
    "pathology": "Générales",
    "patientType": "Adultes",
    "phoneNumber": "01 56 01 64 05",
    "openingDays": "7j sur 7",
    "monday": "24h sur 24",
    "tuesday": "24h sur 24",
    "wednesday": "24h sur 24",
    "thursday": "24h sur 24",
    "friday": "24h sur 24",
    "saturday": "24h sur 24",
    "sunday": "24h sur 24"
  },
  {
    "identifier": 750100273,
    "pathology": "Obstétricales",
    "patientType": "Maternité",
    "phoneNumber": "01 56 01 68 53",
    "openingDays": "7j sur 7",
    "monday": "24h sur 24",
    "tuesday": "24h sur 24",
    "wednesday": "24h sur 24",
    "thursday": "24h sur 24",
    "friday": "24h sur 24",
    "saturday": "24h sur 24",
    "sunday": "24h sur 24"
  },
  {
    "identifier": 750100273,
    "pathology": "Psychiatriques",
    "patientType": "Adultes",
    "phoneNumber": "01 56 01 64 05",
    "openingDays": "7j sur 7",
    "monday": "24h sur 24",
    "tuesday": "24h sur 24",
    "wednesday": "24h sur 24",
    "thursday": "24h sur 24",
    "friday": "24h sur 24",
    "saturday": "24h sur 24",
    "sunday": "24h sur 24"
  },
  {
    "identifier": 750180000,
    "pathology": "Dentaires",
    "patientType": "Adultes",
    "phoneNumber": "01 53 11 14 00",
    "openingDays": "Lun + Mar + Jeu + Ven",
    "monday": "SP 08h00",
    "tuesday": "SP 08h00",
    "wednesday": "",
    "thursday": "SP 08h00",
    "friday": "SP 08h00",
    "saturday": "",
    "sunday": ""
  },
  {
    "identifier": 750180000,
    "pathology": "Dentaires",
    "patientType": "Enfants",
    "phoneNumber": "01 53 11 14 00",
    "openingDays": "Lundi au Mercredi",
    "monday": "SP 08h00 ou 14h00",
    "tuesday": "SP 08h00 ou 14h00",
    "wednesday": "SP 08h00 ou 14h00",
    "thursday": "",
    "friday": "",
    "saturday": "",
    "sunday": ""
  },
  {
    "identifier": 750803447,
    "pathology": "Générales",
    "patientType": "Adultes",
    "phoneNumber": "01 56 09 32 24",
    "openingDays": "7j sur 7",
    "monday": "24h sur 24",
    "tuesday": "24h sur 24",
    "wednesday": "24h sur 24",
    "thursday": "24h sur 24",
    "friday": "24h sur 24",
    "saturday": "24h sur 24",
    "sunday": "24h sur 24"
  },
  {
    "identifier": 750803447,
    "pathology": "Plaies de la main",
    "patientType": "Adultes",
    "phoneNumber": "01 56 09 30 00",
    "openingDays": "7j sur 7",
    "monday": "24h sur 24",
    "tuesday": "24h sur 24",
    "wednesday": "24h sur 24",
    "thursday": "24h sur 24",
    "friday": "24h sur 24",
    "saturday": "24h sur 24",
    "sunday": "24h sur 24"
  },
  {
    "identifier": 750803447,
    "pathology": "Psychiatriques",
    "patientType": "Adultes",
    "phoneNumber": "01 56 09 32 18",
    "openingDays": "7j sur 7",
    "monday": "08h30 - 18h30",
    "tuesday": "08h30 - 18h30",
    "wednesday": "08h30 - 18h30",
    "thursday": "08h30 - 18h30",
    "friday": "08h30 - 18h30",
    "saturday": "08h30 - 18h30",
    "sunday": "08h30 - 18h30"
  },
  {
    "identifier": 750803454,
    "pathology": "Générales",
    "patientType": "Enfants",
    "phoneNumber": "01 40 03 22 70",
    "openingDays": "7j sur 7",
    "monday": "24h sur 24",
    "tuesday": "24h sur 24",
    "wednesday": "24h sur 24",
    "thursday": "24h sur 24",
    "friday": "24h sur 24",
    "saturday": "24h sur 24",
    "sunday": "24h sur 24"
  },
  {
    "identifier": 750803454,
    "pathology": "Psychiatriques",
    "patientType": "Enfants",
    "phoneNumber": "01 40 03 22 70",
    "openingDays": "7j sur 7",
    "monday": "24h sur 24",
    "tuesday": "24h sur 24",
    "wednesday": "24h sur 24",
    "thursday": "24h sur 24",
    "friday": "24h sur 24",
    "saturday": "24h sur 24",
    "sunday": "24h sur 24"
  },
  {
    "identifier": 750803454,
    "pathology": "Plaies de la main",
    "patientType": "Enfants",
    "phoneNumber": "",
    "openingDays": "7j sur 7",
    "monday": "24h sur 24",
    "tuesday": "24h sur 24",
    "wednesday": "24h sur 24",
    "thursday": "24h sur 24",
    "friday": "24h sur 24",
    "saturday": "24h sur 24",
    "sunday": "24h sur 24"
  },
  {
    "identifier": 750803454,
    "pathology": "Gynéco-obstétricales",
    "patientType": "Maternité",
    "phoneNumber": "",
    "openingDays": "7j sur 7",
    "monday": "24h sur 24",
    "tuesday": "24h sur 24",
    "wednesday": "24h sur 24",
    "thursday": "24h sur 24",
    "friday": "24h sur 24",
    "saturday": "24h sur 24",
    "sunday": "24h sur 24"
  },
  {
    "identifier": 920100013,
    "pathology": "Générales",
    "patientType": "Adultes",
    "phoneNumber": "01 49 09 55 18",
    "openingDays": "7j sur 7",
    "monday": "24h sur 24",
    "tuesday": "24h sur 24",
    "wednesday": "24h sur 24",
    "thursday": "24h sur 24",
    "friday": "24h sur 24",
    "saturday": "24h sur 24",
    "sunday": "24h sur 24"
  },
  {
    "identifier": 920100013,
    "pathology": "Générales",
    "patientType": "Enfants",
    "phoneNumber": "01 49 09 57 00",
    "openingDays": "7j sur 7",
    "monday": "24h sur 24",
    "tuesday": "24h sur 24",
    "wednesday": "24h sur 24",
    "thursday": "24h sur 24",
    "friday": "24h sur 24",
    "saturday": "24h sur 24",
    "sunday": "24h sur 24"
  },
  {
    "identifier": 920100013,
    "pathology": "Psychiatriques",
    "patientType": "Adultes",
    "phoneNumber": "01 49 09 55 17",
    "openingDays": "7j sur 7",
    "monday": "24h sur 24",
    "tuesday": "24h sur 24",
    "wednesday": "24h sur 24",
    "thursday": "24h sur 24",
    "friday": "24h sur 24",
    "saturday": "24h sur 24",
    "sunday": "24h sur 24"
  },
  {
    "identifier": 920100021,
    "pathology": "Générales",
    "patientType": "Adultes",
    "phoneNumber": "01 45 37 42 44",
    "openingDays": "7j sur 7",
    "monday": "24h sur 24",
    "tuesday": "24h sur 24",
    "wednesday": "24h sur 24",
    "thursday": "24h sur 24",
    "friday": "24h sur 24",
    "saturday": "24h sur 24",
    "sunday": "24h sur 24"
  },
  {
    "identifier": 920100021,
    "pathology": "Générales",
    "patientType": "Enfants",
    "phoneNumber": "01 45 37 42 44",
    "openingDays": "7j sur 7",
    "monday": "24h sur 24",
    "tuesday": "24h sur 24",
    "wednesday": "24h sur 24",
    "thursday": "24h sur 24",
    "friday": "24h sur 24",
    "saturday": "24h sur 24",
    "sunday": "24h sur 24"
  },
  {
    "identifier": 920100021,
    "pathology": "Gynéco-obstétricales",
    "patientType": "Maternité",
    "phoneNumber": "01 45 37 44 56",
    "openingDays": "7j sur 7",
    "monday": "24h sur 24",
    "tuesday": "24h sur 24",
    "wednesday": "24h sur 24",
    "thursday": "24h sur 24",
    "friday": "24h sur 24",
    "saturday": "24h sur 24",
    "sunday": "24h sur 24"
  },
  {
    "identifier": 920100039,
    "pathology": "Générales",
    "patientType": "Adultes",
    "phoneNumber": "01 40 87 59 40",
    "openingDays": "7j sur 7",
    "monday": "24h sur 24",
    "tuesday": "24h sur 24",
    "wednesday": "24h sur 24",
    "thursday": "24h sur 24",
    "friday": "24h sur 24",
    "saturday": "24h sur 24",
    "sunday": "24h sur 24"
  },
  {
    "identifier": 920100039,
    "pathology": "Gynéco-obstétricales",
    "patientType": "Maternité",
    "phoneNumber": "01 40 87 52 02",
    "openingDays": "7j sur 7",
    "monday": "24h sur 24",
    "tuesday": "24h sur 24",
    "wednesday": "24h sur 24",
    "thursday": "24h sur 24",
    "friday": "24h sur 24",
    "saturday": "24h sur 24",
    "sunday": "24h sur 24"
  },
  {
    "identifier": 920100047,
    "pathology": "Générales",
    "patientType": "Adultes",
    "phoneNumber": "01 47 60 61 54",
    "openingDays": "7j sur 7",
    "monday": "24h sur 24",
    "tuesday": "24h sur 24",
    "wednesday": "24h sur 24",
    "thursday": "24h sur 24",
    "friday": "24h sur 24",
    "saturday": "24h sur 24",
    "sunday": "24h sur 24"
  },
  {
    "identifier": 920100047,
    "pathology": "Générales",
    "patientType": "Enfants",
    "phoneNumber": "01 47 60 60 77",
    "openingDays": "7j sur 7",
    "monday": "24h sur 24",
    "tuesday": "24h sur 24",
    "wednesday": "24h sur 24",
    "thursday": "24h sur 24",
    "friday": "24h sur 24",
    "saturday": "24h sur 24",
    "sunday": "24h sur 24"
  },
  {
    "identifier": 920100047,
    "pathology": "Gynéco-obstétricales",
    "patientType": "Maternité",
    "phoneNumber": "01 47 60 63 45",
    "openingDays": "7j sur 7",
    "monday": "24h sur 24",
    "tuesday": "24h sur 24",
    "wednesday": "24h sur 24",
    "thursday": "24h sur 24",
    "friday": "24h sur 24",
    "saturday": "24h sur 24",
    "sunday": "24h sur 24"
  },
  {
    "identifier": 920100047,
    "pathology": "Dentaires",
    "patientType": "Universel",
    "phoneNumber": "01 47 60 61 74",
    "openingDays": "7j sur 7",
    "monday": "SP 07h30",
    "tuesday": "SP 07h30",
    "wednesday": "SP 07h30",
    "thursday": "SP 07h30",
    "friday": "SP 07h30",
    "saturday": "SP 07h30",
    "sunday": "SP 07h30"
  },
  {
    "identifier": 921300000,
    "pathology": "Psychiatriques",
    "patientType": "Adultes",
    "phoneNumber": "",
    "openingDays": "Lundi au Vendredi",
    "monday": "08h00 - 19h30",
    "tuesday": "08h00 - 19h30",
    "wednesday": "08h00 - 19h30",
    "thursday": "08h00 - 19h30",
    "friday": "08h00 - 19h30",
    "saturday": "",
    "sunday": ""
  },
  {
    "identifier": 930100037,
    "pathology": "Générales",
    "patientType": "Adultes",
    "phoneNumber": "01 48 95 57 83",
    "openingDays": "7j sur 7",
    "monday": "24h sur 24",
    "tuesday": "24h sur 24",
    "wednesday": "24h sur 24",
    "thursday": "24h sur 24",
    "friday": "24h sur 24",
    "saturday": "24h sur 24",
    "sunday": "24h sur 24"
  },
  {
    "identifier": 930100045,
    "pathology": "Générales",
    "patientType": "Adultes",
    "phoneNumber": "01 48 02 65 33",
    "openingDays": "7j sur 7",
    "monday": "24h sur 24",
    "tuesday": "24h sur 24",
    "wednesday": "24h sur 24",
    "thursday": "24h sur 24",
    "friday": "24h sur 24",
    "saturday": "24h sur 24",
    "sunday": "24h sur 24"
  },
  {
    "identifier": 930100045,
    "pathology": "Générales",
    "patientType": "Enfants",
    "phoneNumber": "01 48 02 60 36",
    "openingDays": "7j sur 7",
    "monday": "24h sur 24",
    "tuesday": "24h sur 24",
    "wednesday": "24h sur 24",
    "thursday": "24h sur 24",
    "friday": "24h sur 24",
    "saturday": "24h sur 24",
    "sunday": "24h sur 24"
  },
  {
    "identifier": 930100045,
    "pathology": "Gynéco-obstétricales",
    "patientType": "Maternité",
    "phoneNumber": "01 48 02 67 76",
    "openingDays": "7j sur 7",
    "monday": "24h sur 24",
    "tuesday": "24h sur 24",
    "wednesday": "24h sur 24",
    "thursday": "24h sur 24",
    "friday": "24h sur 24",
    "saturday": "24h sur 24",
    "sunday": "24h sur 24"
  },
  {
    "identifier": 940100027,
    "pathology": "Générales",
    "patientType": "Adultes",
    "phoneNumber": "01 49 81 24 87",
    "openingDays": "7j sur 7",
    "monday": "24h sur 24",
    "tuesday": "24h sur 24",
    "wednesday": "24h sur 24",
    "thursday": "24h sur 24",
    "friday": "24h sur 24",
    "saturday": "24h sur 24",
    "sunday": "24h sur 24"
  },
  {
    "identifier": 940100027,
    "pathology": "Psychiatriques",
    "patientType": "Adultes",
    "phoneNumber": "01 49 81 21 11",
    "openingDays": "7j sur 7",
    "monday": "24h sur 24",
    "tuesday": "24h sur 24",
    "wednesday": "24h sur 24",
    "thursday": "24h sur 24",
    "friday": "24h sur 24",
    "saturday": "24h sur 24",
    "sunday": "24h sur 24"
  },
  {
    "identifier": 940100043,
    "pathology": "Générales",
    "patientType": "Adultes",
    "phoneNumber": "01 45 21 35 42",
    "openingDays": "7j sur 7",
    "monday": "24h sur 24",
    "tuesday": "24h sur 24",
    "wednesday": "24h sur 24",
    "thursday": "24h sur 24",
    "friday": "24h sur 24",
    "saturday": "24h sur 24",
    "sunday": "24h sur 24"
  },
  {
    "identifier": 940100043,
    "pathology": "Générales",
    "patientType": "Enfants",
    "phoneNumber": "01 45 21 29 50",
    "openingDays": "7j sur 7",
    "monday": "24h sur 24",
    "tuesday": "24h sur 24",
    "wednesday": "24h sur 24",
    "thursday": "24h sur 24",
    "friday": "24h sur 24",
    "saturday": "24h sur 24",
    "sunday": "24h sur 24"
  },
  {
    "identifier": 940100043,
    "pathology": "Gynéco-obstétricales",
    "patientType": "Maternité",
    "phoneNumber": "01 45 21 76 06",
    "openingDays": "7j sur 7",
    "monday": "24h sur 24",
    "tuesday": "24h sur 24",
    "wednesday": "24h sur 24",
    "thursday": "24h sur 24",
    "friday": "24h sur 24",
    "saturday": "24h sur 24",
    "sunday": "24h sur 24"
  },
  {
    "identifier": 940100043,
    "pathology": "Psychiatriques",
    "patientType": "Enfants",
    "phoneNumber": "01 45 21 69 40",
    "openingDays": "7j sur 7",
    "monday": "24h sur 24",
    "tuesday": "24h sur 24",
    "wednesday": "24h sur 24",
    "thursday": "24h sur 24",
    "friday": "24h sur 24",
    "saturday": "24h sur 24",
    "sunday": "24h sur 24"
  },
  {
    "identifier": 921400000,
    "pathology": "Générales",
    "patientType": "Adultes",
    "phoneNumber": "01 41 46 62 31",
    "openingDays": "7j sur 7",
    "monday": "24h sur 24",
    "tuesday": "24h sur 24",
    "wednesday": "24h sur 24",
    "thursday": "24h sur 24",
    "friday": "24h sur 24",
    "saturday": "24h sur 24",
    "sunday": "24h sur 24"
  },
  {
    "identifier": 941630000,
    "pathology": "Générales",
    "patientType": "Adultes",
    "phoneNumber": "01 43 98 50 01",
    "openingDays": "7j sur 7",
    "monday": "24h sur 24",
    "tuesday": "24h sur 24",
    "wednesday": "24h sur 24",
    "thursday": "24h sur 24",
    "friday": "24h sur 24",
    "saturday": "24h sur 24",
    "sunday": "24h sur 24"
  },
  {
    "identifier": 941630000,
    "pathology": "Gynéco-obstétricales",
    "patientType": "Maternité",
    "phoneNumber": "01 43 98 59 47",
    "openingDays": "7j sur 7",
    "monday": "24h sur 24",
    "tuesday": "24h sur 24",
    "wednesday": "24h sur 24",
    "thursday": "24h sur 24",
    "friday": "24h sur 24",
    "saturday": "24h sur 24",
    "sunday": "24h sur 24"
  },
  {
    "identifier": 750110025,
    "pathology": "Ophtalmologiques",
    "patientType": "Universel",
    "phoneNumber": "01 40 02 16 80",
    "openingDays": "7j sur 7",
    "monday": "24h sur 24",
    "tuesday": "24h sur 24",
    "wednesday": "24h sur 24",
    "thursday": "24h sur 24",
    "friday": "24h sur 24",
    "saturday": "24h sur 24",
    "sunday": "24h sur 24"
  },
  {
    "identifier": 750140000,
    "pathology": "Psychiatriques",
    "patientType": "Universel",
    "phoneNumber": "01 45 65 81 09",
    "openingDays": "7j sur 7",
    "monday": "24h sur 24",
    "tuesday": "24h sur 24",
    "wednesday": "24h sur 24",
    "thursday": "24h sur 24",
    "friday": "24h sur 24",
    "saturday": "24h sur 24",
    "sunday": "24h sur 24"
  },
  {
    "identifier": 770110013,
    "pathology": "Générales",
    "patientType": "Adultes",
    "phoneNumber": "01 64 65 39 98",
    "openingDays": "7j sur 7",
    "monday": "24h sur 24",
    "tuesday": "24h sur 24",
    "wednesday": "24h sur 24",
    "thursday": "24h sur 24",
    "friday": "24h sur 24",
    "saturday": "24h sur 24",
    "sunday": "24h sur 24"
  },
  {
    "identifier": 770110013,
    "pathology": "Générales",
    "patientType": "Enfants",
    "phoneNumber": "01 64 65 39 98",
    "openingDays": "7j sur 7",
    "monday": "24h sur 24",
    "tuesday": "24h sur 24",
    "wednesday": "24h sur 24",
    "thursday": "24h sur 24",
    "friday": "24h sur 24",
    "saturday": "24h sur 24",
    "sunday": "24h sur 24"
  },
  {
    "identifier": 770110013,
    "pathology": "Générales",
    "patientType": "Enfants",
    "phoneNumber": "01 64 65 39 98",
    "openingDays": "7j sur 7",
    "monday": "24h sur 24",
    "tuesday": "24h sur 24",
    "wednesday": "24h sur 24",
    "thursday": "24h sur 24",
    "friday": "24h sur 24",
    "saturday": "24h sur 24",
    "sunday": "24h sur 24"
  },
  {
    "identifier": 770110021,
    "pathology": "Générales",
    "patientType": "Adultes",
    "phoneNumber": "01 60 74 11 24",
    "openingDays": "7j sur 7",
    "monday": "24h sur 24",
    "tuesday": "24h sur 24",
    "wednesday": "24h sur 24",
    "thursday": "24h sur 24",
    "friday": "24h sur 24",
    "saturday": "24h sur 24",
    "sunday": "24h sur 24"
  },
  {
    "identifier": 770110021,
    "pathology": "Générales",
    "patientType": "Enfants",
    "phoneNumber": "01 60 74 12 88 ",
    "openingDays": "7j sur 7",
    "monday": "24h sur 24",
    "tuesday": "24h sur 24",
    "wednesday": "24h sur 24",
    "thursday": "24h sur 24",
    "friday": "24h sur 24",
    "saturday": "24h sur 24",
    "sunday": "24h sur 24"
  },
  {
    "identifier": 770110021,
    "pathology": "Gynéco-obstétricales",
    "patientType": "Maternité",
    "phoneNumber": "01 60 74 12 64",
    "openingDays": "7j sur 7",
    "monday": "24h sur 24",
    "tuesday": "24h sur 24",
    "wednesday": "24h sur 24",
    "thursday": "24h sur 24",
    "friday": "24h sur 24",
    "saturday": "24h sur 24",
    "sunday": "24h sur 24"
  },
  {
    "identifier": 770110054,
    "pathology": "Générales",
    "patientType": "Adultes",
    "phoneNumber": "",
    "openingDays": "7j sur 7",
    "monday": "24h sur 24",
    "tuesday": "24h sur 24",
    "wednesday": "24h sur 24",
    "thursday": "24h sur 24",
    "friday": "24h sur 24",
    "saturday": "24h sur 24",
    "sunday": "24h sur 24"
  },
  {
    "identifier": 770110054,
    "pathology": "Générales",
    "patientType": "Enfants",
    "phoneNumber": "",
    "openingDays": "7j sur 7",
    "monday": "24h sur 24",
    "tuesday": "24h sur 24",
    "wednesday": "24h sur 24",
    "thursday": "24h sur 24",
    "friday": "24h sur 24",
    "saturday": "24h sur 24",
    "sunday": "24h sur 24"
  },
  {
    "identifier": 770110054,
    "pathology": "Gynéco-obstétricales",
    "patientType": "Maternité",
    "phoneNumber": "",
    "openingDays": "7j sur 7",
    "monday": "24h sur 24",
    "tuesday": "24h sur 24",
    "wednesday": "24h sur 24",
    "thursday": "24h sur 24",
    "friday": "24h sur 24",
    "saturday": "24h sur 24",
    "sunday": "24h sur 24"
  },
  {
    "identifier": 770110062,
    "pathology": "Générales",
    "patientType": "Universel",
    "phoneNumber": "01 64 31 65 36",
    "openingDays": "7j sur 7",
    "monday": "24h sur 24",
    "tuesday": "24h sur 24",
    "wednesday": "24h sur 24",
    "thursday": "24h sur 24",
    "friday": "24h sur 24",
    "saturday": "24h sur 24",
    "sunday": "24h sur 24"
  },
  {
    "identifier": 770110062,
    "pathology": "Gynéco-obstétricales",
    "patientType": "Maternité",
    "phoneNumber": "01 64 31 65 85",
    "openingDays": "Lundi au Vendredi",
    "monday": "09h00 - 16h00",
    "tuesday": "09h00 - 16h00",
    "wednesday": "09h00 - 16h00",
    "thursday": "09h00 - 16h00",
    "friday": "09h00 - 16h00",
    "saturday": "",
    "sunday": ""
  },
  {
    "identifier": 770110070,
    "pathology": "Générales",
    "patientType": "Adultes",
    "phoneNumber": "01 64 60 40 50",
    "openingDays": "7j sur 7",
    "monday": "24h sur 24",
    "tuesday": "24h sur 24",
    "wednesday": "24h sur 24",
    "thursday": "24h sur 24",
    "friday": "24h sur 24",
    "saturday": "24h sur 24",
    "sunday": "24h sur 24"
  },
  {
    "identifier": 770110070,
    "pathology": "Générales",
    "patientType": "Enfants",
    "phoneNumber": "01 64 60 35 94",
    "openingDays": "7j sur 7",
    "monday": "24h sur 24",
    "tuesday": "24h sur 24",
    "wednesday": "24h sur 24",
    "thursday": "24h sur 24",
    "friday": "24h sur 24",
    "saturday": "24h sur 24",
    "sunday": "24h sur 24"
  },
  {
    "identifier": 770110070,
    "pathology": "Gynéco-obstétricales",
    "patientType": "Maternité",
    "phoneNumber": "01 64 60 40 56",
    "openingDays": "7j sur 7",
    "monday": "24h sur 24",
    "tuesday": "24h sur 24",
    "wednesday": "24h sur 24",
    "thursday": "24h sur 24",
    "friday": "24h sur 24",
    "saturday": "24h sur 24",
    "sunday": "24h sur 24"
  },
  {
    "identifier": 770130052,
    "pathology": "Générales",
    "patientType": "Adultes",
    "phoneNumber": "01 64 45 19 37",
    "openingDays": "7j sur 7",
    "monday": "24h sur 24",
    "tuesday": "24h sur 24",
    "wednesday": "24h sur 24",
    "thursday": "24h sur 24",
    "friday": "24h sur 24",
    "saturday": "24h sur 24",
    "sunday": "24h sur 24"
  },
  {
    "identifier": 770170017,
    "pathology": "Générales",
    "patientType": "Adultes",
    "phoneNumber": "01 61 10 61 10",
    "openingDays": "7j sur 7",
    "monday": "24h sur 24",
    "tuesday": "24h sur 24",
    "wednesday": "24h sur 24",
    "thursday": "24h sur 24",
    "friday": "24h sur 24",
    "saturday": "24h sur 24",
    "sunday": "24h sur 24"
  },
  {
    "identifier": 770170017,
    "pathology": "Générales",
    "patientType": "Enfants",
    "phoneNumber": "01 61 10 61 10",
    "openingDays": "7j sur 7",
    "monday": "24h sur 24",
    "tuesday": "24h sur 24",
    "wednesday": "24h sur 24",
    "thursday": "24h sur 24",
    "friday": "24h sur 24",
    "saturday": "24h sur 24",
    "sunday": "24h sur 24"
  },
  {
    "identifier": 770170017,
    "pathology": "Gynéco-obstétricales",
    "patientType": "Maternité",
    "phoneNumber": "01 61 10 60 24",
    "openingDays": "7j sur 7",
    "monday": "24h sur 24",
    "tuesday": "24h sur 24",
    "wednesday": "24h sur 24",
    "thursday": "24h sur 24",
    "friday": "24h sur 24",
    "saturday": "24h sur 24",
    "sunday": "24h sur 24"
  },
  {
    "identifier": 770700185,
    "pathology": "Générales",
    "patientType": "Adultes",
    "phoneNumber": "01 64 35 39 80",
    "openingDays": "7j sur 7",
    "monday": "24h sur 24",
    "tuesday": "24h sur 24",
    "wednesday": "24h sur 24",
    "thursday": "24h sur 24",
    "friday": "24h sur 24",
    "saturday": "24h sur 24",
    "sunday": "24h sur 24"
  },
  {
    "identifier": 770700185,
    "pathology": "Générales",
    "patientType": "Enfants",
    "phoneNumber": "01 64 35 37 66",
    "openingDays": "7j sur 7",
    "monday": "24h sur 24",
    "tuesday": "24h sur 24",
    "wednesday": "24h sur 24",
    "thursday": "24h sur 24",
    "friday": "24h sur 24",
    "saturday": "24h sur 24",
    "sunday": "24h sur 24"
  },
  {
    "identifier": 770700185,
    "pathology": "Gynéco-obstétricales",
    "patientType": "Maternité",
    "phoneNumber": "01 64 35 38 71",
    "openingDays": "7j sur 7",
    "monday": "24h sur 24",
    "tuesday": "24h sur 24",
    "wednesday": "24h sur 24",
    "thursday": "24h sur 24",
    "friday": "24h sur 24",
    "saturday": "24h sur 24",
    "sunday": "24h sur 24"
  },
  {
    "identifier": 780000311,
    "pathology": "Générales",
    "patientType": "Adultes",
    "phoneNumber": "01 39 27 51 18",
    "openingDays": "7j sur 7",
    "monday": "24h sur 24",
    "tuesday": "24h sur 24",
    "wednesday": "24h sur 24",
    "thursday": "24h sur 24",
    "friday": "24h sur 24",
    "saturday": "24h sur 24",
    "sunday": "24h sur 24"
  },
  {
    "identifier": 780000311,
    "pathology": "Générales",
    "patientType": "Enfants",
    "phoneNumber": "01 39 27 55 91",
    "openingDays": "7j sur 7",
    "monday": "24h sur 24",
    "tuesday": "24h sur 24",
    "wednesday": "24h sur 24",
    "thursday": "24h sur 24",
    "friday": "24h sur 24",
    "saturday": "24h sur 24",
    "sunday": "24h sur 24"
  },
  {
    "identifier": 780000311,
    "pathology": "Gynéco-obstétricales",
    "patientType": "Maternité",
    "phoneNumber": "01 39 27 53 79",
    "openingDays": "7j sur 7",
    "monday": "24h sur 24",
    "tuesday": "24h sur 24",
    "wednesday": "24h sur 24",
    "thursday": "24h sur 24",
    "friday": "24h sur 24",
    "saturday": "24h sur 24",
    "sunday": "24h sur 24"
  },
  {
    "identifier": 780000312,
    "pathology": "Générales",
    "patientType": "Adultes",
    "phoneNumber": "01 39 27 41 00",
    "openingDays": "Lundi au Vendredi",
    "monday": "09h00 - 18h00",
    "tuesday": "09h00 - 18h00",
    "wednesday": "09h00 - 18h00",
    "thursday": "09h00 - 18h00",
    "friday": "09h00 - 18h00",
    "saturday": "",
    "sunday": ""
  },
  {
    "identifier": 780002697,
    "pathology": "Générales",
    "patientType": "Adultes",
    "phoneNumber": "",
    "openingDays": "7j sur 7",
    "monday": "24h sur 24",
    "tuesday": "24h sur 24",
    "wednesday": "24h sur 24",
    "thursday": "24h sur 24",
    "friday": "24h sur 24",
    "saturday": "24h sur 24",
    "sunday": "24h sur 24"
  },
  {
    "identifier": 780002697,
    "pathology": "Gynéco-obstétricales",
    "patientType": "Maternité",
    "phoneNumber": "01 30 22 41 92",
    "openingDays": "7j sur 7",
    "monday": "24h sur 24",
    "tuesday": "24h sur 24",
    "wednesday": "24h sur 24",
    "thursday": "24h sur 24",
    "friday": "24h sur 24",
    "saturday": "24h sur 24",
    "sunday": "24h sur 24"
  },
  {
    "identifier": 780110011,
    "pathology": "Générales",
    "patientType": "Adultes",
    "phoneNumber": "01 34 97 42 92",
    "openingDays": "7j sur 7",
    "monday": "24h sur 24",
    "tuesday": "24h sur 24",
    "wednesday": "24h sur 24",
    "thursday": "24h sur 24",
    "friday": "24h sur 24",
    "saturday": "24h sur 24",
    "sunday": "24h sur 24"
  },
  {
    "identifier": 780110011,
    "pathology": "Générales",
    "patientType": "Enfants",
    "phoneNumber": "01 34 97 33 26",
    "openingDays": "7j sur 7",
    "monday": "24h sur 24",
    "tuesday": "24h sur 24",
    "wednesday": "24h sur 24",
    "thursday": "24h sur 24",
    "friday": "24h sur 24",
    "saturday": "24h sur 24",
    "sunday": "24h sur 24"
  },
  {
    "identifier": 780110011,
    "pathology": "Gynéco-obstétricales",
    "patientType": "Maternité",
    "phoneNumber": "01 34 97 41 49",
    "openingDays": "7j sur 7",
    "monday": "24h sur 24",
    "tuesday": "24h sur 24",
    "wednesday": "24h sur 24",
    "thursday": "24h sur 24",
    "friday": "24h sur 24",
    "saturday": "24h sur 24",
    "sunday": "24h sur 24"
  },
  {
    "identifier": 780110052,
    "pathology": "Générales",
    "patientType": "Adultes",
    "phoneNumber": "01 34 83 68 44",
    "openingDays": "7j sur 7",
    "monday": "24h sur 24",
    "tuesday": "24h sur 24",
    "wednesday": "24h sur 24",
    "thursday": "24h sur 24",
    "friday": "24h sur 24",
    "saturday": "24h sur 24",
    "sunday": "24h sur 24"
  },
  {
    "identifier": 780110052,
    "pathology": "Générales",
    "patientType": "Enfants",
    "phoneNumber": "01 34 83 77 96",
    "openingDays": "7j sur 7",
    "monday": "24h sur 24",
    "tuesday": "24h sur 24",
    "wednesday": "24h sur 24",
    "thursday": "24h sur 24",
    "friday": "24h sur 24",
    "saturday": "24h sur 24",
    "sunday": "24h sur 24"
  },
  {
    "identifier": 780110052,
    "pathology": "Obstétricales",
    "patientType": "Maternité",
    "phoneNumber": "01 34 83 77 15",
    "openingDays": "7j sur 7",
    "monday": "24h sur 24",
    "tuesday": "24h sur 24",
    "wednesday": "24h sur 24",
    "thursday": "24h sur 24",
    "friday": "24h sur 24",
    "saturday": "24h sur 24",
    "sunday": "24h sur 24"
  },
  {
    "identifier": 780110078,
    "pathology": "Générales",
    "patientType": "Universel",
    "phoneNumber": "01 39 63 88 45",
    "openingDays": "7j sur 7",
    "monday": "24h sur 24",
    "tuesday": "24h sur 24",
    "wednesday": "24h sur 24",
    "thursday": "24h sur 24",
    "friday": "24h sur 24",
    "saturday": "24h sur 24",
    "sunday": "24h sur 24"
  },
  {
    "identifier": 780110078,
    "pathology": "Obstétricales",
    "patientType": "Maternité",
    "phoneNumber": "",
    "openingDays": "7j sur 7",
    "monday": "24h sur 24",
    "tuesday": "24h sur 24",
    "wednesday": "24h sur 24",
    "thursday": "24h sur 24",
    "friday": "24h sur 24",
    "saturday": "24h sur 24",
    "sunday": "24h sur 24"
  },
  {
    "identifier": 910000280,
    "pathology": "Générales",
    "patientType": "Adultes",
    "phoneNumber": "",
    "openingDays": "7j sur 7",
    "monday": "24h sur 24",
    "tuesday": "24h sur 24",
    "wednesday": "24h sur 24",
    "thursday": "24h sur 24",
    "friday": "24h sur 24",
    "saturday": "24h sur 24",
    "sunday": "24h sur 24"
  },
  {
    "identifier": 910000280,
    "pathology": "Générales",
    "patientType": "Enfants",
    "phoneNumber": "",
    "openingDays": "7j sur 7",
    "monday": "24h sur 24",
    "tuesday": "24h sur 24",
    "wednesday": "24h sur 24",
    "thursday": "24h sur 24",
    "friday": "24h sur 24",
    "saturday": "24h sur 24",
    "sunday": "24h sur 24"
  },
  {
    "identifier": 910000314,
    "pathology": "Générales",
    "patientType": "Adultes",
    "phoneNumber": "",
    "openingDays": "7j sur 7",
    "monday": "24h sur 24",
    "tuesday": "24h sur 24",
    "wednesday": "24h sur 24",
    "thursday": "24h sur 24",
    "friday": "24h sur 24",
    "saturday": "24h sur 24",
    "sunday": "24h sur 24"
  },
  {
    "identifier": 910000314,
    "pathology": "Générales",
    "patientType": "Enfants",
    "phoneNumber": "",
    "openingDays": "7j sur 7",
    "monday": "24h sur 24",
    "tuesday": "24h sur 24",
    "wednesday": "24h sur 24",
    "thursday": "24h sur 24",
    "friday": "24h sur 24",
    "saturday": "24h sur 24",
    "sunday": "24h sur 24"
  },
  {
    "identifier": 910000314,
    "pathology": "Gynéco-obstétricales",
    "patientType": "Maternité",
    "phoneNumber": "",
    "openingDays": "7j sur 7",
    "monday": "24h sur 24",
    "tuesday": "24h sur 24",
    "wednesday": "24h sur 24",
    "thursday": "24h sur 24",
    "friday": "24h sur 24",
    "saturday": "24h sur 24",
    "sunday": "24h sur 24"
  },
  {
    "identifier": 910001973,
    "pathology": "Générales",
    "patientType": "Universel",
    "phoneNumber": "",
    "openingDays": "7j sur 7",
    "monday": "24h sur 24",
    "tuesday": "24h sur 24",
    "wednesday": "24h sur 24",
    "thursday": "24h sur 24",
    "friday": "24h sur 24",
    "saturday": "24h sur 24",
    "sunday": "24h sur 24"
  },
  {
    "identifier": 910001973,
    "pathology": "Obstétricales",
    "patientType": "Maternité",
    "phoneNumber": "",
    "openingDays": "7j sur 7",
    "monday": "24h sur 24",
    "tuesday": "24h sur 24",
    "wednesday": "24h sur 24",
    "thursday": "24h sur 24",
    "friday": "24h sur 24",
    "saturday": "24h sur 24",
    "sunday": "24h sur 24"
  },
  {
    "identifier": 910019454,
    "pathology": "Générales",
    "patientType": "Universel",
    "phoneNumber": "01 69 54 27 00",
    "openingDays": "7j sur 7",
    "monday": "24h sur 24",
    "tuesday": "24h sur 24",
    "wednesday": "24h sur 24",
    "thursday": "24h sur 24",
    "friday": "24h sur 24",
    "saturday": "24h sur 24",
    "sunday": "24h sur 24"
  },
  {
    "identifier": 910110014,
    "pathology": "Générales",
    "patientType": "Universel",
    "phoneNumber": "",
    "openingDays": "7j sur 7",
    "monday": "24h sur 24",
    "tuesday": "24h sur 24",
    "wednesday": "24h sur 24",
    "thursday": "24h sur 24",
    "friday": "24h sur 24",
    "saturday": "24h sur 24",
    "sunday": "24h sur 24"
  },
  {
    "identifier": 910110014,
    "pathology": "Gynéco-obstétricales",
    "patientType": "Maternité",
    "phoneNumber": "",
    "openingDays": "7j sur 7",
    "monday": "24h sur 24",
    "tuesday": "24h sur 24",
    "wednesday": "24h sur 24",
    "thursday": "24h sur 24",
    "friday": "24h sur 24",
    "saturday": "24h sur 24",
    "sunday": "24h sur 24"
  },
  {
    "identifier": 910110055,
    "pathology": "Générales",
    "patientType": "Adultes",
    "phoneNumber": "01 64 54 30 36",
    "openingDays": "7j sur 7",
    "monday": "24h sur 24",
    "tuesday": "24h sur 24",
    "wednesday": "24h sur 24",
    "thursday": "24h sur 24",
    "friday": "24h sur 24",
    "saturday": "24h sur 24",
    "sunday": "24h sur 24"
  },
  {
    "identifier": 910110055,
    "pathology": "Générales",
    "patientType": "Enfants",
    "phoneNumber": "01 64 54 30 06",
    "openingDays": "7j sur 7",
    "monday": "24h sur 24",
    "tuesday": "24h sur 24",
    "wednesday": "24h sur 24",
    "thursday": "24h sur 24",
    "friday": "24h sur 24",
    "saturday": "24h sur 24",
    "sunday": "24h sur 24"
  },
  {
    "identifier": 910110055,
    "pathology": "Gynéco-obstétricales",
    "patientType": "Maternité",
    "phoneNumber": "01 64 54 87 87",
    "openingDays": "7j sur 7",
    "monday": "24h sur 24",
    "tuesday": "24h sur 24",
    "wednesday": "24h sur 24",
    "thursday": "24h sur 24",
    "friday": "24h sur 24",
    "saturday": "24h sur 24",
    "sunday": "24h sur 24"
  },
  {
    "identifier": 910110063,
    "pathology": "Générales",
    "patientType": "Adultes",
    "phoneNumber": "01 69 29 75 62",
    "openingDays": "7j sur 7",
    "monday": "24h sur 24",
    "tuesday": "24h sur 24",
    "wednesday": "24h sur 24",
    "thursday": "24h sur 24",
    "friday": "24h sur 24",
    "saturday": "24h sur 24",
    "sunday": "24h sur 24"
  },
  {
    "identifier": 910110063,
    "pathology": "Générales",
    "patientType": "Enfants",
    "phoneNumber": "01 69 29 76 06",
    "openingDays": "7j sur 7",
    "monday": "24h sur 24",
    "tuesday": "24h sur 24",
    "wednesday": "24h sur 24",
    "thursday": "24h sur 24",
    "friday": "24h sur 24",
    "saturday": "24h sur 24",
    "sunday": "24h sur 24"
  },
  {
    "identifier": 910110063,
    "pathology": "Gynéco-obstétricales",
    "patientType": "Maternité",
    "phoneNumber": "01 69 29 75 85",
    "openingDays": "7j sur 7",
    "monday": "24h sur 24",
    "tuesday": "24h sur 24",
    "wednesday": "24h sur 24",
    "thursday": "24h sur 24",
    "friday": "24h sur 24",
    "saturday": "24h sur 24",
    "sunday": "24h sur 24"
  },
  {
    "identifier": 920000585,
    "pathology": "Générales",
    "patientType": "Universel",
    "phoneNumber": "01 40 88 62 23",
    "openingDays": "7j sur 7",
    "monday": "24h sur 24",
    "tuesday": "24h sur 24",
    "wednesday": "24h sur 24",
    "thursday": "24h sur 24",
    "friday": "24h sur 24",
    "saturday": "24h sur 24",
    "sunday": "24h sur 24"
  },
  {
    "identifier": 920000585,
    "pathology": "Obstétricales",
    "patientType": "Maternité",
    "phoneNumber": "01 40 88 61 64",
    "openingDays": "7j sur 7",
    "monday": "24h sur 24",
    "tuesday": "24h sur 24",
    "wednesday": "24h sur 24",
    "thursday": "24h sur 24",
    "friday": "24h sur 24",
    "saturday": "24h sur 24",
    "sunday": "24h sur 24"
  },
  {
    "identifier": 920000619,
    "pathology": "Générales",
    "patientType": "Universel",
    "phoneNumber": "",
    "openingDays": "7j sur 7",
    "monday": "24h sur 24",
    "tuesday": "24h sur 24",
    "wednesday": "24h sur 24",
    "thursday": "24h sur 24",
    "friday": "24h sur 24",
    "saturday": "24h sur 24",
    "sunday": "24h sur 24"
  },
  {
    "identifier": 920000619,
    "pathology": "Obstétricales",
    "patientType": "Maternité",
    "phoneNumber": "",
    "openingDays": "7j sur 7",
    "monday": "24h sur 24",
    "tuesday": "24h sur 24",
    "wednesday": "24h sur 24",
    "thursday": "24h sur 24",
    "friday": "24h sur 24",
    "saturday": "24h sur 24",
    "sunday": "24h sur 24"
  },
  {
    "identifier": 920110020,
    "pathology": "Générales",
    "patientType": "Adultes",
    "phoneNumber": "01 47 69 66 34",
    "openingDays": "7j sur 7",
    "monday": "24h sur 24",
    "tuesday": "24h sur 24",
    "wednesday": "24h sur 24",
    "thursday": "24h sur 24",
    "friday": "24h sur 24",
    "saturday": "24h sur 24",
    "sunday": "24h sur 24"
  },
  {
    "identifier": 920110020,
    "pathology": "Gynéco-obstétricales",
    "patientType": "Maternité",
    "phoneNumber": "01 47 69 66 41",
    "openingDays": "7j sur 7",
    "monday": "24h sur 24",
    "tuesday": "24h sur 24",
    "wednesday": "24h sur 24",
    "thursday": "24h sur 24",
    "friday": "24h sur 24",
    "saturday": "24h sur 24",
    "sunday": "24h sur 24"
  },
  {
    "identifier": 930021480,
    "pathology": "",
    "patientType": "Universel",
    "phoneNumber": "",
    "openingDays": "",
    "monday": "",
    "tuesday": "",
    "wednesday": "",
    "thursday": "",
    "friday": "",
    "saturday": "",
    "sunday": ""
  },
  {
    "identifier": 930110036,
    "pathology": "Générales",
    "patientType": "Adultes",
    "phoneNumber": "01 49 20 30 75",
    "openingDays": "7j sur 7",
    "monday": "24h sur 24",
    "tuesday": "24h sur 24",
    "wednesday": "24h sur 24",
    "thursday": "24h sur 24",
    "friday": "24h sur 24",
    "saturday": "24h sur 24",
    "sunday": "24h sur 24"
  },
  {
    "identifier": 930110036,
    "pathology": "Générales",
    "patientType": "Enfants",
    "phoneNumber": "01 49 20 30 75",
    "openingDays": "7j sur 7",
    "monday": "24h sur 24",
    "tuesday": "24h sur 24",
    "wednesday": "24h sur 24",
    "thursday": "24h sur 24",
    "friday": "24h sur 24",
    "saturday": "24h sur 24",
    "sunday": "24h sur 24"
  },
  {
    "identifier": 930110036,
    "pathology": "Gynéco-obstétricales",
    "patientType": "Maternité",
    "phoneNumber": "01 49 20 71 32",
    "openingDays": "7j sur 7",
    "monday": "24h sur 24",
    "tuesday": "24h sur 24",
    "wednesday": "24h sur 24",
    "thursday": "24h sur 24",
    "friday": "24h sur 24",
    "saturday": "24h sur 24",
    "sunday": "24h sur 24"
  },
  {
    "identifier": 930110051,
    "pathology": "Générales",
    "patientType": "Adultes",
    "phoneNumber": "01 42 35 61 15",
    "openingDays": "7j sur 7",
    "monday": "24h sur 24",
    "tuesday": "24h sur 24",
    "wednesday": "24h sur 24",
    "thursday": "24h sur 24",
    "friday": "24h sur 24",
    "saturday": "24h sur 24",
    "sunday": "24h sur 24"
  },
  {
    "identifier": 930110051,
    "pathology": "Générales",
    "patientType": "Enfants",
    "phoneNumber": "01 42 35 60 94",
    "openingDays": "7j sur 7",
    "monday": "24h sur 24",
    "tuesday": "24h sur 24",
    "wednesday": "24h sur 24",
    "thursday": "24h sur 24",
    "friday": "24h sur 24",
    "saturday": "24h sur 24",
    "sunday": "24h sur 24"
  },
  {
    "identifier": 930110051,
    "pathology": "Gynéco-obstétricales",
    "patientType": "Maternité",
    "phoneNumber": "01 42 35 61 61",
    "openingDays": "7j sur 7",
    "monday": "24h sur 24",
    "tuesday": "24h sur 24",
    "wednesday": "24h sur 24",
    "thursday": "24h sur 24",
    "friday": "24h sur 24",
    "saturday": "24h sur 24",
    "sunday": "24h sur 24"
  },
  {
    "identifier": 930110069,
    "pathology": "Générales",
    "patientType": "Universel",
    "phoneNumber": "01 49 36 72 12",
    "openingDays": "7j sur 7",
    "monday": "24h sur 24",
    "tuesday": "24h sur 24",
    "wednesday": "24h sur 24",
    "thursday": "24h sur 24",
    "friday": "24h sur 24",
    "saturday": "24h sur 24",
    "sunday": "24h sur 24"
  },
  {
    "identifier": 930110069,
    "pathology": "Gynéco-obstétricales",
    "patientType": "Maternité",
    "phoneNumber": "01 75 63 60 62",
    "openingDays": "7j sur 7",
    "monday": "24h sur 24",
    "tuesday": "24h sur 24",
    "wednesday": "24h sur 24",
    "thursday": "24h sur 24",
    "friday": "24h sur 24",
    "saturday": "24h sur 24",
    "sunday": "24h sur 24"
  },
  {
    "identifier": 940110018,
    "pathology": "Générales",
    "patientType": "Adultes",
    "phoneNumber": "01 57 02 24 50",
    "openingDays": "7j sur 7",
    "monday": "24h sur 24",
    "tuesday": "24h sur 24",
    "wednesday": "24h sur 24",
    "thursday": "24h sur 24",
    "friday": "24h sur 24",
    "saturday": "24h sur 24",
    "sunday": "24h sur 24"
  },
  {
    "identifier": 940110018,
    "pathology": "Générales",
    "patientType": "Enfants",
    "phoneNumber": "01 57 02 24 65",
    "openingDays": "7j sur 7",
    "monday": "24h sur 24",
    "tuesday": "24h sur 24",
    "wednesday": "24h sur 24",
    "thursday": "24h sur 24",
    "friday": "24h sur 24",
    "saturday": "24h sur 24",
    "sunday": "24h sur 24"
  },
  {
    "identifier": 940110018,
    "pathology": "Gynéco-obstétricales",
    "patientType": "Maternité",
    "phoneNumber": "01 45 17 55 55",
    "openingDays": "7j sur 7",
    "monday": "24h sur 24",
    "tuesday": "24h sur 24",
    "wednesday": "24h sur 24",
    "thursday": "24h sur 24",
    "friday": "24h sur 24",
    "saturday": "24h sur 24",
    "sunday": "24h sur 24"
  },
  {
    "identifier": 940110042,
    "pathology": "Générales",
    "patientType": "Adultes",
    "phoneNumber": "01 43 86 22 01",
    "openingDays": "7j sur 7",
    "monday": "24h sur 24",
    "tuesday": "24h sur 24",
    "wednesday": "24h sur 24",
    "thursday": "24h sur 24",
    "friday": "24h sur 24",
    "saturday": "24h sur 24",
    "sunday": "24h sur 24"
  },
  {
    "identifier": 940110042,
    "pathology": "Générales",
    "patientType": "Enfants",
    "phoneNumber": "01 43 86 21 93",
    "openingDays": "7j sur 7",
    "monday": "24h sur 24",
    "tuesday": "24h sur 24",
    "wednesday": "24h sur 24",
    "thursday": "24h sur 24",
    "friday": "24h sur 24",
    "saturday": "24h sur 24",
    "sunday": "24h sur 24"
  },
  {
    "identifier": 940110042,
    "pathology": "Obstétricales",
    "patientType": "Maternité",
    "phoneNumber": "01 43 86 21 54",
    "openingDays": "7j sur 7",
    "monday": "24h sur 24",
    "tuesday": "24h sur 24",
    "wednesday": "24h sur 24",
    "thursday": "24h sur 24",
    "friday": "24h sur 24",
    "saturday": "24h sur 24",
    "sunday": "24h sur 24"
  },
  {
    "identifier": 940110042,
    "pathology": "Ophtalmologiques",
    "patientType": "Universel",
    "phoneNumber": "01 43 86 20 17",
    "openingDays": "7j sur 7",
    "monday": "24h sur 24",
    "tuesday": "24h sur 24",
    "wednesday": "24h sur 24",
    "thursday": "24h sur 24",
    "friday": "24h sur 24",
    "saturday": "24h sur 24",
    "sunday": "24h sur 24"
  },
  {
    "identifier": 950000315,
    "pathology": "Générales",
    "patientType": "Adultes",
    "phoneNumber": "01 39 37 14 73",
    "openingDays": "7j sur 7",
    "monday": "24h sur 24",
    "tuesday": "24h sur 24",
    "wednesday": "24h sur 24",
    "thursday": "24h sur 24",
    "friday": "24h sur 24",
    "saturday": "24h sur 24",
    "sunday": "24h sur 24"
  },
  {
    "identifier": 950000315,
    "pathology": "Générales",
    "patientType": "Enfants",
    "phoneNumber": "01 39 37 14 73",
    "openingDays": "7j sur 7",
    "monday": "24h sur 24",
    "tuesday": "24h sur 24",
    "wednesday": "24h sur 24",
    "thursday": "24h sur 24",
    "friday": "24h sur 24",
    "saturday": "24h sur 24",
    "sunday": "24h sur 24"
  },
  {
    "identifier": 950000315,
    "pathology": "Gynéco-obstétricales",
    "patientType": "Maternité",
    "phoneNumber": "01 39 37 14 27",
    "openingDays": "7j sur 7",
    "monday": "24h sur 24",
    "tuesday": "24h sur 24",
    "wednesday": "24h sur 24",
    "thursday": "24h sur 24",
    "friday": "24h sur 24",
    "saturday": "24h sur 24",
    "sunday": "24h sur 24"
  },
  {
    "identifier": 950000356,
    "pathology": "Générales",
    "patientType": "Adultes",
    "phoneNumber": "01 34 06 61 16",
    "openingDays": "7j sur 7",
    "monday": "24h sur 24",
    "tuesday": "24h sur 24",
    "wednesday": "24h sur 24",
    "thursday": "24h sur 24",
    "friday": "24h sur 24",
    "saturday": "24h sur 24",
    "sunday": "24h sur 24"
  },
  {
    "identifier": 950000356,
    "pathology": "Générales",
    "patientType": "Enfants",
    "phoneNumber": "01 34 06 61 61",
    "openingDays": "7j sur 7",
    "monday": "24h sur 24",
    "tuesday": "24h sur 24",
    "wednesday": "24h sur 24",
    "thursday": "24h sur 24",
    "friday": "24h sur 24",
    "saturday": "24h sur 24",
    "sunday": "24h sur 24"
  },
  {
    "identifier": 950000356,
    "pathology": "Gynéco-obstétricales",
    "patientType": "Maternité",
    "phoneNumber": "01 34 06 61 61",
    "openingDays": "7j sur 7",
    "monday": "24h sur 24",
    "tuesday": "24h sur 24",
    "wednesday": "24h sur 24",
    "thursday": "24h sur 24",
    "friday": "24h sur 24",
    "saturday": "24h sur 24",
    "sunday": "24h sur 24"
  },
  {
    "identifier": 950015289,
    "pathology": "Générales",
    "patientType": "Universel",
    "phoneNumber": "01 34 79 44 45",
    "openingDays": "7j sur 7",
    "monday": "24h sur 24",
    "tuesday": "24h sur 24",
    "wednesday": "24h sur 24",
    "thursday": "24h sur 24",
    "friday": "24h sur 24",
    "saturday": "24h sur 24",
    "sunday": "24h sur 24"
  },
  {
    "identifier": 950110015,
    "pathology": "Générales",
    "patientType": "Adultes",
    "phoneNumber": "01 34 23 26 05",
    "openingDays": "7j sur 7",
    "monday": "24h sur 24",
    "tuesday": "24h sur 24",
    "wednesday": "24h sur 24",
    "thursday": "24h sur 24",
    "friday": "24h sur 24",
    "saturday": "24h sur 24",
    "sunday": "24h sur 24"
  },
  {
    "identifier": 950110015,
    "pathology": "Générales",
    "patientType": "Enfants",
    "phoneNumber": "01 34 23 26 05",
    "openingDays": "7j sur 7",
    "monday": "24h sur 24",
    "tuesday": "24h sur 24",
    "wednesday": "24h sur 24",
    "thursday": "24h sur 24",
    "friday": "24h sur 24",
    "saturday": "24h sur 24",
    "sunday": "24h sur 24"
  },
  {
    "identifier": 950110015,
    "pathology": "Gynéco-obstétricales",
    "patientType": "Maternité",
    "phoneNumber": "01 34 23 17 34",
    "openingDays": "7j sur 7",
    "monday": "24h sur 24",
    "tuesday": "24h sur 24",
    "wednesday": "24h sur 24",
    "thursday": "24h sur 24",
    "friday": "24h sur 24",
    "saturday": "24h sur 24",
    "sunday": "24h sur 24"
  },
  {
    "identifier": 950110015,
    "pathology": "Psychiatriques",
    "patientType": "Universel",
    "phoneNumber": "01 34 23 20 01",
    "openingDays": "7j sur 7",
    "monday": "24h sur 24",
    "tuesday": "24h sur 24",
    "wednesday": "24h sur 24",
    "thursday": "24h sur 24",
    "friday": "24h sur 24",
    "saturday": "24h sur 24",
    "sunday": "24h sur 24"
  },
  {
    "identifier": 950110049,
    "pathology": "Générales",
    "patientType": "Adultes",
    "phoneNumber": "01 34 53 20 43",
    "openingDays": "7j sur 7",
    "monday": "24h sur 24",
    "tuesday": "24h sur 24",
    "wednesday": "24h sur 24",
    "thursday": "24h sur 24",
    "friday": "24h sur 24",
    "saturday": "24h sur 24",
    "sunday": "24h sur 24"
  },
  {
    "identifier": 950110049,
    "pathology": "Générales",
    "patientType": "Enfants",
    "phoneNumber": "01 34 53 23 73",
    "openingDays": "7j sur 7",
    "monday": "24h sur 24",
    "tuesday": "24h sur 24",
    "wednesday": "24h sur 24",
    "thursday": "24h sur 24",
    "friday": "24h sur 24",
    "saturday": "24h sur 24",
    "sunday": "24h sur 24"
  },
  {
    "identifier": 950110049,
    "pathology": "Gynéco-obstétricales",
    "patientType": "Maternité",
    "phoneNumber": "01 34 53 21 36",
    "openingDays": "7j sur 7",
    "monday": "24h sur 24",
    "tuesday": "24h sur 24",
    "wednesday": "24h sur 24",
    "thursday": "24h sur 24",
    "friday": "24h sur 24",
    "saturday": "24h sur 24",
    "sunday": "24h sur 24"
  },
  {
    "identifier": 950110049,
    "pathology": "Psychiatriques",
    "patientType": "Universel",
    "phoneNumber": "01 34 53 22 99",
    "openingDays": "7j sur 7",
    "monday": "24h sur 24",
    "tuesday": "24h sur 24",
    "wednesday": "24h sur 24",
    "thursday": "24h sur 24",
    "friday": "24h sur 24",
    "saturday": "24h sur 24",
    "sunday": "24h sur 24"
  },
  {
    "identifier": 950110080,
    "pathology": "Générales",
    "patientType": "Adultes",
    "phoneNumber": "01 30 75 43 66",
    "openingDays": "7j sur 7",
    "monday": "24h sur 24",
    "tuesday": "24h sur 24",
    "wednesday": "24h sur 24",
    "thursday": "24h sur 24",
    "friday": "24h sur 24",
    "saturday": "24h sur 24",
    "sunday": "24h sur 24"
  },
  {
    "identifier": 950110080,
    "pathology": "Générales",
    "patientType": "Enfants",
    "phoneNumber": "01 30 75 40 03",
    "openingDays": "7j sur 7",
    "monday": "24h sur 24",
    "tuesday": "24h sur 24",
    "wednesday": "24h sur 24",
    "thursday": "24h sur 24",
    "friday": "24h sur 24",
    "saturday": "24h sur 24",
    "sunday": "24h sur 24"
  },
  {
    "identifier": 950110080,
    "pathology": "Gynéco-obstétricales",
    "patientType": "Maternité",
    "phoneNumber": "01 30 75 48 71",
    "openingDays": "7j sur 7",
    "monday": "24h sur 24",
    "tuesday": "24h sur 24",
    "wednesday": "24h sur 24",
    "thursday": "24h sur 24",
    "friday": "24h sur 24",
    "saturday": "24h sur 24",
    "sunday": "24h sur 24"
  },
  {
    "identifier": 950110080,
    "pathology": "Psychiatriques",
    "patientType": "Adultes",
    "phoneNumber": "01 30 75 43 26",
    "openingDays": "7j sur 7",
    "monday": "24h sur 24",
    "tuesday": "24h sur 24",
    "wednesday": "24h sur 24",
    "thursday": "24h sur 24",
    "friday": "24h sur 24",
    "saturday": "24h sur 24",
    "sunday": "24h sur 24"
  },
  {
    "identifier": 750000523,
    "pathology": "Générales",
    "patientType": "Adultes",
    "phoneNumber": "",
    "openingDays": "7j sur 7",
    "monday": "24h sur 24",
    "tuesday": "24h sur 24",
    "wednesday": "24h sur 24",
    "thursday": "24h sur 24",
    "friday": "24h sur 24",
    "saturday": "24h sur 24",
    "sunday": "24h sur 24"
  },
  {
    "identifier": 750000523,
    "pathology": "Gynéco-obstétricales",
    "patientType": "Maternité",
    "phoneNumber": "01 44 12 81 70",
    "openingDays": "7j sur 7",
    "monday": "24h sur 24",
    "tuesday": "24h sur 24",
    "wednesday": "24h sur 24",
    "thursday": "24h sur 24",
    "friday": "24h sur 24",
    "saturday": "24h sur 24",
    "sunday": "24h sur 24"
  },
  {
    "identifier": 750000523,
    "pathology": "Proctologiques",
    "patientType": "Adultes",
    "phoneNumber": "",
    "openingDays": "Lundi au Samedi",
    "monday": "09h00 - 18h00",
    "tuesday": "09h00 - 18h00",
    "wednesday": "09h00 - 18h00",
    "thursday": "09h00 - 18h00",
    "friday": "09h00 - 18h00",
    "saturday": "09h00 - 12h00",
    "sunday": ""
  },
  {
    "identifier": 750000523,
    "pathology": "Psychiatriques",
    "patientType": "Adultes",
    "phoneNumber": "01 44 12 37 86",
    "openingDays": "7j sur 7",
    "monday": "24h sur 24",
    "tuesday": "24h sur 24",
    "wednesday": "24h sur 24",
    "thursday": "24h sur 24",
    "friday": "24h sur 24",
    "saturday": "24h sur 24",
    "sunday": "24h sur 24"
  },
  {
    "identifier": 750000549,
    "pathology": "Ophtalmologiques",
    "patientType": "Universel",
    "phoneNumber": "01 48 03 68 84 ",
    "openingDays": "7j sur 7",
    "monday": "24h sur 24",
    "tuesday": "24h sur 24",
    "wednesday": "24h sur 24",
    "thursday": "24h sur 24",
    "friday": "24h sur 24",
    "saturday": "24h sur 24",
    "sunday": "24h sur 24"
  },
  {
    "identifier": 750150260,
    "pathology": "Générales",
    "patientType": "Adultes",
    "phoneNumber": "01 44 64 17 13",
    "openingDays": "7j sur 7",
    "monday": "24h sur 24",
    "tuesday": "24h sur 24",
    "wednesday": "24h sur 24",
    "thursday": "24h sur 24",
    "friday": "24h sur 24",
    "saturday": "24h sur 24",
    "sunday": "24h sur 24"
  },
  {
    "identifier": 750150260,
    "pathology": "Proctologiques",
    "patientType": "Adultes",
    "phoneNumber": "01 44 64 17 13",
    "openingDays": "Lundi au Vendredi",
    "monday": "09h00 - 18h00",
    "tuesday": "09h00 - 13h00",
    "wednesday": "09h00 - 13h00",
    "thursday": "09h00 - 13h00",
    "friday": "09h00 - 18h00",
    "saturday": "",
    "sunday": ""
  },
  {
    "identifier": 750150261,
    "pathology": "Obstétricales",
    "patientType": "Maternité",
    "phoneNumber": "01 44 74 10 10",
    "openingDays": "7j sur 7",
    "monday": "24h sur 24",
    "tuesday": "24h sur 24",
    "wednesday": "24h sur 24",
    "thursday": "24h sur 24",
    "friday": "24h sur 24",
    "saturday": "24h sur 24",
    "sunday": "24h sur 24"
  },
  {
    "identifier": 780000436,
    "pathology": "Générales",
    "patientType": "Adultes",
    "phoneNumber": "01 30 86 36 22",
    "openingDays": "7j sur 7",
    "monday": "24h sur 24",
    "tuesday": "24h sur 24",
    "wednesday": "24h sur 24",
    "thursday": "24h sur 24",
    "friday": "24h sur 24",
    "saturday": "24h sur 24",
    "sunday": "24h sur 24"
  },
  {
    "identifier": 920000643,
    "pathology": "Générales",
    "patientType": "Adultes",
    "phoneNumber": "01 47 59 59 59",
    "openingDays": "7j sur 7",
    "monday": "24h sur 24",
    "tuesday": "24h sur 24",
    "wednesday": "24h sur 24",
    "thursday": "24h sur 24",
    "friday": "24h sur 24",
    "saturday": "24h sur 24",
    "sunday": "24h sur 24"
  },
  {
    "identifier": 920000643,
    "pathology": "Générales",
    "patientType": "Enfants",
    "phoneNumber": "01 47 59 59 59",
    "openingDays": "7j sur 7",
    "monday": "24h sur 24",
    "tuesday": "24h sur 24",
    "wednesday": "24h sur 24",
    "thursday": "24h sur 24",
    "friday": "24h sur 24",
    "saturday": "24h sur 24",
    "sunday": "24h sur 24"
  },
  {
    "identifier": 920000644,
    "pathology": "Gynéco-obstétricales",
    "patientType": "Maternité",
    "phoneNumber": "01 46 39 22 22",
    "openingDays": "7j sur 7",
    "monday": "24h sur 24",
    "tuesday": "24h sur 24",
    "wednesday": "24h sur 24",
    "thursday": "24h sur 24",
    "friday": "24h sur 24",
    "saturday": "24h sur 24",
    "sunday": "24h sur 24"
  },
  {
    "identifier": 920000650,
    "pathology": "Générales",
    "patientType": "Adultes",
    "phoneNumber": "01 46 25 20 29",
    "openingDays": "7j sur 7",
    "monday": "24h sur 24",
    "tuesday": "24h sur 24",
    "wednesday": "24h sur 24",
    "thursday": "24h sur 24",
    "friday": "24h sur 24",
    "saturday": "24h sur 24",
    "sunday": "24h sur 24"
  },
  {
    "identifier": 920000650,
    "pathology": "Gynéco-obstétricales",
    "patientType": "Maternité",
    "phoneNumber": "01 46 25 28 74",
    "openingDays": "7j sur 7",
    "monday": "24h sur 24",
    "tuesday": "24h sur 24",
    "wednesday": "24h sur 24",
    "thursday": "24h sur 24",
    "friday": "24h sur 24",
    "saturday": "24h sur 24",
    "sunday": "24h sur 24"
  },
  {
    "identifier": 940000649,
    "pathology": "Générales",
    "patientType": "Adultes",
    "phoneNumber": "01 49 83 10 86",
    "openingDays": "7j sur 7",
    "monday": "24h sur 24",
    "tuesday": "24h sur 24",
    "wednesday": "24h sur 24",
    "thursday": "24h sur 24",
    "friday": "24h sur 24",
    "saturday": "24h sur 24",
    "sunday": "24h sur 24"
  },
  {
    "identifier": 940000649,
    "pathology": "Générales",
    "patientType": "Enfants",
    "phoneNumber": "01 49 83 10 05",
    "openingDays": "7j sur 7",
    "monday": "24h sur 24",
    "tuesday": "24h sur 24",
    "wednesday": "24h sur 24",
    "thursday": "24h sur 24",
    "friday": "24h sur 24",
    "saturday": "24h sur 24",
    "sunday": "24h sur 24"
  },
  {
    "identifier": 750170000,
    "pathology": "Plaies de la main",
    "patientType": "Universel",
    "phoneNumber": "01 48 88 26 37",
    "openingDays": "Lundi au Samedi",
    "monday": "09h00 - 19h00",
    "tuesday": "09h00 - 19h00",
    "wednesday": "09h00 - 19h00",
    "thursday": "09h00 - 19h00",
    "friday": "09h00 - 19h00",
    "saturday": "09h00 - 18h00",
    "sunday": ""
  },
  {
    "identifier": 770300135,
    "pathology": "Générales",
    "patientType": "Adultes",
    "phoneNumber": "",
    "openingDays": "7j sur 7",
    "monday": "24h sur 24",
    "tuesday": "24h sur 24",
    "wednesday": "24h sur 24",
    "thursday": "24h sur 24",
    "friday": "24h sur 24",
    "saturday": "24h sur 24",
    "sunday": "24h sur 24"
  },
  {
    "identifier": 770790707,
    "pathology": "Générales",
    "patientType": "Adultes",
    "phoneNumber": "",
    "openingDays": "7j sur 7",
    "monday": "24h sur 24",
    "tuesday": "24h sur 24",
    "wednesday": "24h sur 24",
    "thursday": "24h sur 24",
    "friday": "24h sur 24",
    "saturday": "24h sur 24",
    "sunday": "24h sur 24"
  },
  {
    "identifier": 771770000,
    "pathology": "Générales",
    "patientType": "Adultes",
    "phoneNumber": "",
    "openingDays": "7j sur 7",
    "monday": "24h sur 24",
    "tuesday": "24h sur 24",
    "wednesday": "24h sur 24",
    "thursday": "24h sur 24",
    "friday": "24h sur 24",
    "saturday": "24h sur 24",
    "sunday": "24h sur 24"
  },
  {
    "identifier": 773400000,
    "pathology": "Générales",
    "patientType": "Adultes",
    "phoneNumber": "01 64 43 43 43",
    "openingDays": "7j sur 7",
    "monday": "08h00 - 22h30",
    "tuesday": "08h00 - 22h30",
    "wednesday": "08h00 - 22h30",
    "thursday": "08h00 - 22h30",
    "friday": "08h00 - 22h30",
    "saturday": "08h00 - 22h30",
    "sunday": "08h00 - 22h30"
  },
  {
    "identifier": 780300323,
    "pathology": "Générales",
    "patientType": "Adultes",
    "phoneNumber": "01 30 97 33 18",
    "openingDays": "7j sur 7",
    "monday": "24h sur 24",
    "tuesday": "24h sur 24",
    "wednesday": "24h sur 24",
    "thursday": "24h sur 24",
    "friday": "24h sur 24",
    "saturday": "24h sur 24",
    "sunday": "24h sur 24"
  },
  {
    "identifier": 780300323,
    "pathology": "Gynéco-obstétricales",
    "patientType": "Maternité",
    "phoneNumber": "",
    "openingDays": "7j sur 7",
    "monday": "24h sur 24",
    "tuesday": "24h sur 24",
    "wednesday": "24h sur 24",
    "thursday": "24h sur 24",
    "friday": "24h sur 24",
    "saturday": "24h sur 24",
    "sunday": "24h sur 24"
  },
  {
    "identifier": 780300406,
    "pathology": "Générales",
    "patientType": "Adultes",
    "phoneNumber": "01 39 63 71 15",
    "openingDays": "7j sur 7",
    "monday": "24h sur 24",
    "tuesday": "24h sur 24",
    "wednesday": "24h sur 24",
    "thursday": "24h sur 24",
    "friday": "24h sur 24",
    "saturday": "24h sur 24",
    "sunday": "24h sur 24"
  },
  {
    "identifier": 780300406,
    "pathology": "Gynéco-obstétricales",
    "patientType": "Maternité",
    "phoneNumber": "08 25 74 35 05",
    "openingDays": "7j sur 7",
    "monday": "24h sur 24",
    "tuesday": "24h sur 24",
    "wednesday": "24h sur 24",
    "thursday": "24h sur 24",
    "friday": "24h sur 24",
    "saturday": "24h sur 24",
    "sunday": "24h sur 24"
  },
  {
    "identifier": 780300414,
    "pathology": "Générales",
    "patientType": "Adultes",
    "phoneNumber": "01 39 17 24 24",
    "openingDays": "7j sur 7",
    "monday": "24h sur 24",
    "tuesday": "24h sur 24",
    "wednesday": "24h sur 24",
    "thursday": "24h sur 24",
    "friday": "24h sur 24",
    "saturday": "24h sur 24",
    "sunday": "24h sur 24"
  },
  {
    "identifier": 780300422,
    "pathology": "Générales",
    "patientType": "Adultes",
    "phoneNumber": "01 30 69 45 13",
    "openingDays": "7j sur 7",
    "monday": "24h sur 24",
    "tuesday": "24h sur 24",
    "wednesday": "24h sur 24",
    "thursday": "24h sur 24",
    "friday": "24h sur 24",
    "saturday": "24h sur 24",
    "sunday": "24h sur 24"
  },
  {
    "identifier": 780300422,
    "pathology": "Obstétricales",
    "patientType": "Maternité",
    "phoneNumber": "",
    "openingDays": "7j sur 7",
    "monday": "24h sur 24",
    "tuesday": "24h sur 24",
    "wednesday": "24h sur 24",
    "thursday": "24h sur 24",
    "friday": "24h sur 24",
    "saturday": "24h sur 24",
    "sunday": "24h sur 24"
  },
  {
    "identifier": 780300422,
    "pathology": "Plaies de la main",
    "patientType": "Universel",
    "phoneNumber": "01 30 69 48 22",
    "openingDays": "7j sur 7",
    "monday": "24h sur 24",
    "tuesday": "24h sur 24",
    "wednesday": "24h sur 24",
    "thursday": "24h sur 24",
    "friday": "24h sur 24",
    "saturday": "24h sur 24",
    "sunday": "24h sur 24"
  },
  {
    "identifier": 780300455,
    "pathology": "Générales",
    "patientType": "Adultes",
    "phoneNumber": "01 30 95 10 27",
    "openingDays": "7j sur 7",
    "monday": "24h sur 24",
    "tuesday": "24h sur 24",
    "wednesday": "24h sur 24",
    "thursday": "24h sur 24",
    "friday": "24h sur 24",
    "saturday": "24h sur 24",
    "sunday": "24h sur 24"
  },
  {
    "identifier": 780300455,
    "pathology": "Plaies de la main",
    "patientType": "Universel",
    "phoneNumber": "08 10 01 50 15",
    "openingDays": "7j sur 7",
    "monday": "24h sur 24",
    "tuesday": "24h sur 24",
    "wednesday": "24h sur 24",
    "thursday": "24h sur 24",
    "friday": "24h sur 24",
    "saturday": "24h sur 24",
    "sunday": "24h sur 24"
  },
  {
    "identifier": 783000000,
    "pathology": "Générales",
    "patientType": "Adultes",
    "phoneNumber": "01 30 74 88 23",
    "openingDays": "Lundi au Samedi",
    "monday": "09h00 - 19h00",
    "tuesday": "09h00 - 19h00",
    "wednesday": "09h00 - 19h00",
    "thursday": "09h00 - 19h00",
    "friday": "09h00 - 19h00",
    "saturday": "09h00 - 19h00",
    "sunday": ""
  },
  {
    "identifier": 783000000,
    "pathology": "Gynéco-obstétricales",
    "patientType": "Adultes",
    "phoneNumber": "01 30 74 88 23",
    "openingDays": "Lundi au Samedi",
    "monday": "09h00 - 19h00",
    "tuesday": "09h00 - 19h00",
    "wednesday": "09h00 - 19h00",
    "thursday": "09h00 - 19h00",
    "friday": "09h00 - 19h00",
    "saturday": "09h00 - 19h00",
    "sunday": ""
  },
  {
    "identifier": 910300144,
    "pathology": "Générales",
    "patientType": "Adultes",
    "phoneNumber": "01 60 90 10 65",
    "openingDays": "7j sur 7",
    "monday": "24h sur 24",
    "tuesday": "24h sur 24",
    "wednesday": "24h sur 24",
    "thursday": "24h sur 24",
    "friday": "24h sur 24",
    "saturday": "24h sur 24",
    "sunday": "24h sur 24"
  },
  {
    "identifier": 910300219,
    "pathology": "Générales",
    "patientType": "Adultes",
    "phoneNumber": "01 60 13 62 92",
    "openingDays": "7j sur 7",
    "monday": "24h sur 24",
    "tuesday": "24h sur 24",
    "wednesday": "24h sur 24",
    "thursday": "24h sur 24",
    "friday": "24h sur 24",
    "saturday": "24h sur 24",
    "sunday": "24h sur 24"
  },
  {
    "identifier": 910300300,
    "pathology": "Générales",
    "patientType": "Adultes",
    "phoneNumber": "01 69 49 73 50",
    "openingDays": "7j sur 7",
    "monday": "24h sur 24",
    "tuesday": "24h sur 24",
    "wednesday": "24h sur 24",
    "thursday": "24h sur 24",
    "friday": "24h sur 24",
    "saturday": "24h sur 24",
    "sunday": "24h sur 24"
  },
  {
    "identifier": 910803543,
    "pathology": "Générales",
    "patientType": "Adultes",
    "phoneNumber": "01 69 39 90 15",
    "openingDays": "7j sur 7",
    "monday": "24h sur 24",
    "tuesday": "24h sur 24",
    "wednesday": "24h sur 24",
    "thursday": "24h sur 24",
    "friday": "24h sur 24",
    "saturday": "24h sur 24",
    "sunday": "24h sur 24"
  },
  {
    "identifier": 920300043,
    "pathology": "Générales",
    "patientType": "Adultes",
    "phoneNumber": "",
    "openingDays": "7j sur 7",
    "monday": "24h sur 24",
    "tuesday": "24h sur 24",
    "wednesday": "24h sur 24",
    "thursday": "24h sur 24",
    "friday": "24h sur 24",
    "saturday": "24h sur 24",
    "sunday": "24h sur 24"
  },
  {
    "identifier": 923600000,
    "pathology": "Générales",
    "patientType": "Adultes",
    "phoneNumber": "",
    "openingDays": "7j sur 7",
    "monday": "24h sur 24",
    "tuesday": "24h sur 24",
    "wednesday": "24h sur 24",
    "thursday": "24h sur 24",
    "friday": "24h sur 24",
    "saturday": "24h sur 24",
    "sunday": "24h sur 24"
  },
  {
    "identifier": 930300025,
    "pathology": "Générales",
    "patientType": "Adultes",
    "phoneNumber": "01 48 39 42 62",
    "openingDays": "7j sur 7",
    "monday": "24h sur 24",
    "tuesday": "24h sur 24",
    "wednesday": "24h sur 24",
    "thursday": "24h sur 24",
    "friday": "24h sur 24",
    "saturday": "24h sur 24",
    "sunday": "24h sur 24"
  },
  {
    "identifier": 930300066,
    "pathology": "Générales",
    "patientType": "Adultes",
    "phoneNumber": "01 48 19 33 34",
    "openingDays": "7j sur 7",
    "monday": "24h sur 24",
    "tuesday": "24h sur 24",
    "wednesday": "24h sur 24",
    "thursday": "24h sur 24",
    "friday": "24h sur 24",
    "saturday": "24h sur 24",
    "sunday": "24h sur 24"
  },
  {
    "identifier": 930300082,
    "pathology": "Générales",
    "patientType": "Adultes",
    "phoneNumber": "01 48 97 73 00",
    "openingDays": "7j sur 7",
    "monday": "24h sur 24",
    "tuesday": "24h sur 24",
    "wednesday": "24h sur 24",
    "thursday": "24h sur 24",
    "friday": "24h sur 24",
    "saturday": "24h sur 24",
    "sunday": "24h sur 24"
  },
  {
    "identifier": 930300082,
    "pathology": "Plaies de la main",
    "patientType": "Universel",
    "phoneNumber": "01 48 97 72 08",
    "openingDays": "7j sur 7",
    "monday": "24h sur 24",
    "tuesday": "24h sur 24",
    "wednesday": "24h sur 24",
    "thursday": "24h sur 24",
    "friday": "24h sur 24",
    "saturday": "24h sur 24",
    "sunday": "24h sur 24"
  },
  {
    "identifier": 930300116,
    "pathology": "Générales",
    "patientType": "Adultes",
    "phoneNumber": "",
    "openingDays": "7j sur 7",
    "monday": "24h sur 24",
    "tuesday": "24h sur 24",
    "wednesday": "24h sur 24",
    "thursday": "24h sur 24",
    "friday": "24h sur 24",
    "saturday": "24h sur 24",
    "sunday": "24h sur 24"
  },
  {
    "identifier": 930300553,
    "pathology": "Générales",
    "patientType": "Adultes",
    "phoneNumber": "01 49 71 90 00",
    "openingDays": "7j sur 7",
    "monday": "24h sur 24",
    "tuesday": "24h sur 24",
    "wednesday": "24h sur 24",
    "thursday": "24h sur 24",
    "friday": "24h sur 24",
    "saturday": "24h sur 24",
    "sunday": "24h sur 24"
  },
  {
    "identifier": 930300553,
    "pathology": "Obstétricales",
    "patientType": "Maternité",
    "phoneNumber": "01 49 71 92 13",
    "openingDays": "7j sur 7",
    "monday": "24h sur 24",
    "tuesday": "24h sur 24",
    "wednesday": "24h sur 24",
    "thursday": "24h sur 24",
    "friday": "24h sur 24",
    "saturday": "24h sur 24",
    "sunday": "24h sur 24"
  },
  {
    "identifier": 930300595,
    "pathology": "Générales",
    "patientType": "Adultes",
    "phoneNumber": "01 49 63 50 15",
    "openingDays": "7j sur 7",
    "monday": "24h sur 24",
    "tuesday": "24h sur 24",
    "wednesday": "24h sur 24",
    "thursday": "24h sur 24",
    "friday": "24h sur 24",
    "saturday": "24h sur 24",
    "sunday": "24h sur 24"
  },
  {
    "identifier": 930300595,
    "pathology": "Gynéco-obstétricales",
    "patientType": "Maternité",
    "phoneNumber": "",
    "openingDays": "7j sur 7",
    "monday": "24h sur 24",
    "tuesday": "24h sur 24",
    "wednesday": "24h sur 24",
    "thursday": "24h sur 24",
    "friday": "24h sur 24",
    "saturday": "24h sur 24",
    "sunday": "24h sur 24"
  },
  {
    "identifier": 930300595,
    "pathology": "Plaies de la main",
    "patientType": "Universel",
    "phoneNumber": "01 49 63 50 15",
    "openingDays": "7j sur 7",
    "monday": "24h sur 24",
    "tuesday": "24h sur 24",
    "wednesday": "24h sur 24",
    "thursday": "24h sur 24",
    "friday": "24h sur 24",
    "saturday": "24h sur 24",
    "sunday": "24h sur 24"
  },
  {
    "identifier": 940300031,
    "pathology": "Générales",
    "patientType": "Adultes",
    "phoneNumber": "01 49 83 67 11",
    "openingDays": "7j sur 7",
    "monday": "24h sur 24",
    "tuesday": "24h sur 24",
    "wednesday": "24h sur 24",
    "thursday": "24h sur 24",
    "friday": "24h sur 24",
    "saturday": "24h sur 24",
    "sunday": "24h sur 24"
  },
  {
    "identifier": 940300031,
    "pathology": "Plaies de la main",
    "patientType": "Universel",
    "phoneNumber": "01 49 83 67 11",
    "openingDays": "7j sur 7",
    "monday": "24h sur 24",
    "tuesday": "24h sur 24",
    "wednesday": "24h sur 24",
    "thursday": "24h sur 24",
    "friday": "24h sur 24",
    "saturday": "24h sur 24",
    "sunday": "24h sur 24"
  },
  {
    "identifier": 940300270,
    "pathology": "Générales",
    "patientType": "Adultes",
    "phoneNumber": "01 48 71 50 50",
    "openingDays": "7j sur 7",
    "monday": "24h sur 24",
    "tuesday": "24h sur 24",
    "wednesday": "24h sur 24",
    "thursday": "24h sur 24",
    "friday": "24h sur 24",
    "saturday": "24h sur 24",
    "sunday": "24h sur 24"
  },
  {
    "identifier": 940300445,
    "pathology": "Générales",
    "patientType": "Adultes",
    "phoneNumber": "01 45 60 28 00",
    "openingDays": "7j sur 7",
    "monday": "24h sur 24",
    "tuesday": "24h sur 24",
    "wednesday": "24h sur 24",
    "thursday": "24h sur 24",
    "friday": "24h sur 24",
    "saturday": "24h sur 24",
    "sunday": "24h sur 24"
  },
  {
    "identifier": 940300569,
    "pathology": "Gynéco-obstétricales",
    "patientType": "Maternité",
    "phoneNumber": "01 46 77 03 94",
    "openingDays": "7j sur 7",
    "monday": "24h sur 24",
    "tuesday": "24h sur 24",
    "wednesday": "24h sur 24",
    "thursday": "24h sur 24",
    "friday": "24h sur 24",
    "saturday": "24h sur 24",
    "sunday": "24h sur 24"
  },
  {
    "identifier": 940300570,
    "pathology": "Générales",
    "patientType": "Adultes",
    "phoneNumber": "01 45 73 35 36",
    "openingDays": "7j sur 7",
    "monday": "24h sur 24",
    "tuesday": "24h sur 24",
    "wednesday": "24h sur 24",
    "thursday": "24h sur 24",
    "friday": "24h sur 24",
    "saturday": "24h sur 24",
    "sunday": "24h sur 24"
  },
  {
    "identifier": 950300277,
    "pathology": "Générales",
    "patientType": "Adultes",
    "phoneNumber": "01 39 33 77 80",
    "openingDays": "7j sur 7",
    "monday": "24h sur 24",
    "tuesday": "24h sur 24",
    "wednesday": "24h sur 24",
    "thursday": "24h sur 24",
    "friday": "24h sur 24",
    "saturday": "24h sur 24",
    "sunday": "24h sur 24"
  },
  {
    "identifier": 950300277,
    "pathology": "Obstétricales",
    "patientType": "Maternité",
    "phoneNumber": "01 39 33 77 80",
    "openingDays": "7j sur 7",
    "monday": "24h sur 24",
    "tuesday": "24h sur 24",
    "wednesday": "24h sur 24",
    "thursday": "24h sur 24",
    "friday": "24h sur 24",
    "saturday": "24h sur 24",
    "sunday": "24h sur 24"
  },
  {
    "identifier": 950807982,
    "pathology": "Générales",
    "patientType": "Adultes",
    "phoneNumber": "",
    "openingDays": "7j sur 7",
    "monday": "24h sur 24",
    "tuesday": "24h sur 24",
    "wednesday": "24h sur 24",
    "thursday": "24h sur 24",
    "friday": "24h sur 24",
    "saturday": "24h sur 24",
    "sunday": "24h sur 24"
  }
]
